wiz_tts/__init__.py
wiz_tts/audio.py
wiz_tts/cli.py
wiz_tts/tts.py
wiz_tts/voices.py
wiz_tts/tts_adapters/groq_tts.py
wiz_tts/tts_adapters/openai_tts.py
wiz_tts-0.5.0.dist-info/METADATA
wiz_tts-0.5.0.dist-info/WHEEL
wiz_tts-0.5.0.dist-info/entry_points.txt
wiz_tts-0.5.0.dist-info/top_level.txt
wiz_tts-0.5.0.dist-info/RECORD
