Metadata-Version: 2.4
Name: wiz-tts
Version: 0.5.0
Summary: A simple CLI tool for text-to-speech using OpenAI's API
Requires-Python: >=3.13
Requires-Dist: numpy>=2.2.4
Requires-Dist: openai>=1.75.0
Requires-Dist: groq==0.22.0
Requires-Dist: rich>=14.0.0
Requires-Dist: sounddevice>=0.5.1
Requires-Dist: scipy>=1.12.0
Requires-Dist: pydub>=0.25.1
Requires-Dist: audioop-lts>=0.2.1
